Metadata-Version: 2.1
Name: Akinator-python
Version: 1.6.0
Summary: A API wrapper for the AkinatorAPI
Home-page: https://github.com/taka-4602/Akinator-python
Author: taka4602
Author-email: shun4602@gmail.com
Keywords: akinator
Classifier: Programming Language :: Python :: 3
Classifier: License :: OSI Approved :: MIT License
Classifier: Operating System :: OS Independent
Requires-Python: >=3.6
